flare/__init__.py
flare/alerting.py
flare/constraints.py
flare/examples.py
flare/generators.py
flare/runtime.py
flare/statistics.py
flare/types.py
domino_flare-0.1.0.dist-info/METADATA
domino_flare-0.1.0.dist-info/WHEEL
domino_flare-0.1.0.dist-info/top_level.txt
domino_flare-0.1.0.dist-info/RECORD
